{"_id":"array-some","_rev":"2-829e771cd23e2f8d27e63477dcc4762e","name":"array-some","description":"Array#some ponyfill for older browsers","dist-tags":{"latest":"1.0.0"},"versions":{"1.0.0":{"name":"array-some","description":"Array#some ponyfill for older browsers","version":"1.0.0","author":{"name":"Takuto Wada","email":"takuto.wada@gmail.com","url":"https://github.com/twada"},"bugs":{"url":"https://github.com/twada/array-some/issues"},"devDependencies":{"jshint":"^2.6.3","mocha":"^2.2.1"},"files":["README.md","index.js","build/array-some.js","package.json","test"],"homepage":"https://github.com/twada/array-some","keywords":["array","browser","es5","ie6","ie7","ie8","polyfill","ponyfill","shim","some"],"license":{"type":"MIT","url":"http://twada.mit-license.org/"},"main":"index.js","repository":{"type":"git","url":"git://github.com/twada/array-some.git"},"scripts":{"build":"browserify index.js --standalone some | dereserve | derequire > ./build/array-some.js","lint":"jshint index.js","test":"npm run lint && mocha"},"gitHead":"979f787223f84ecbb65b33f5ad050ee43f429f9a","_id":"array-some@1.0.0","_shasum":"037f6ac6c9056c6531c4ceb16997c588cbfaf684","_from":".","_npmVersion":"2.5.1","_nodeVersion":"0.12.0","_npmUser":{"name":"twada","email":"takuto.wada@gmail.com"},"maintainers":[{"name":"twada","email":"takuto.wada@gmail.com"}],"dist":{"shasum":"037f6ac6c9056c6531c4ceb16997c588cbfaf684","tarball":"https://registry.npmjs.org/array-some/-/array-some-1.0.0.tgz"},"directories":{}}},"readme":"array-some\n================================\n\n[![Build Status][travis-image]][travis-url]\n[![NPM package][npm-image]][npm-url]\n[![Bower package][bower-image]][bower-url]\n[![Dependency Status][depstat-image]][depstat-url]\n[![License][license-image]][license-url]\n\n\nArray#some ponyfill for older browsers\n\n> Ponyfill: A polyfill that doesn't overwrite the native method\n\n\nDESCRIPTION\n---------------------------------------\n\nProvides `some` function for older browsers, use native implememtation if exists.\n\nIt's just like\n\n- [array-foreach](https://www.npmjs.org/package/array-foreach)\n- [array-map](https://www.npmjs.org/package/array-map)\n- [array-filter](https://www.npmjs.org/package/array-filter)\n- [array-reduce](https://www.npmjs.org/package/array-reduce)\n- [indexof](https://www.npmjs.org/package/indexof)\n- [object-assign](https://www.npmjs.com/package/object-assign)\n\n\nEXAMPLE\n---------------------------------------\n\n```javascript\nvar some = require('array-some');\nfunction isBiggerThan10 (element, index, array) {\n    return element > 10;\n}\nsome([2, 5, 8, 1, 4], isBiggerThan10);  // false\nsome([12, 5, 8, 1, 4], isBiggerThan10); // true\n```\n\n\nINSTALL\n---------------------------------------\n\n### via npm\n\nInstall\n\n    $ npm install --save array-some\n\nUse\n\n```javascript\nvar some = require('array-some');\n```\n\n### via bower\n\nInstall\n\n    $ bower install --save array-some\n\nLoad (`some` function is exported)\n\n    <script type=\"text/javascript\" src=\"./path/to/bower_components/array-some/build/array-some.js\"></script>\n\nUse\n\n```javascript\nvar result = some([2, 5, 8, 1, 4], function (element, index, array) {\n    return element > 10;\n});\n```\n\n\nAUTHOR\n---------------------------------------\n* [Takuto Wada](http://github.com/twada)\n\n\nLICENSE\n---------------------------------------\nLicensed under the [MIT](http://twada.mit-license.org/) license.\n\n\n[travis-url]: http://travis-ci.org/twada/array-some\n[travis-image]: https://secure.travis-ci.org/twada/array-some.svg?branch=master\n\n[npm-url]: https://npmjs.org/package/array-some\n[npm-image]: https://badge.fury.io/js/array-some.svg\n\n[bower-url]: http://badge.fury.io/bo/array-some\n[bower-image]: https://badge.fury.io/bo/array-some.svg\n\n[depstat-url]: https://gemnasium.com/twada/array-some\n[depstat-image]: https://gemnasium.com/twada/array-some.svg\n\n[license-url]: http://twada.mit-license.org/\n[license-image]: http://img.shields.io/badge/license-MIT-brightgreen.svg\n","maintainers":[{"name":"twada","email":"takuto.wada@gmail.com"}],"time":{"modified":"2015-03-09T10:58:45.362Z","created":"2015-03-09T10:58:45.362Z","1.0.0":"2015-03-09T10:58:45.362Z"},"homepage":"https://github.com/twada/array-some","keywords":["array","browser","es5","ie6","ie7","ie8","polyfill","ponyfill","shim","some"],"repository":{"type":"git","url":"git://github.com/twada/array-some.git"},"author":{"name":"Takuto Wada","email":"takuto.wada@gmail.com","url":"https://github.com/twada"},"bugs":{"url":"https://github.com/twada/array-some/issues"},"license":{"type":"MIT","url":"http://twada.mit-license.org/"},"readmeFilename":"README.md","_attachments":{},"_etag":"\"BYJAI8GCPPIS2XVY8MM10BWU8\""}